clean_py/__init__.py
clean_py/_version.py
clean_py/clean_py.py
clean_py/cli.py
clean_py-1.0.1.post2.dist-info/licenses/LICENSE
clean_py-1.0.1.post2.dist-info/METADATA
clean_py-1.0.1.post2.dist-info/WHEEL
clean_py-1.0.1.post2.dist-info/entry_points.txt
clean_py-1.0.1.post2.dist-info/top_level.txt
clean_py-1.0.1.post2.dist-info/RECORD
