Metadata-Version: 2.4
Name: clean-py
Version: 1.0.1.post2
Summary: CLI tool for automated Python code cleanup and standardization
Author-email: Sam Hardy <samhardyhey@gmail.com>
License: MIT License
Project-URL: Homepage, https://github.com/samhardyhey/clean-py
Project-URL: Repository, https://github.com/samhardyhey/clean-py.git
Project-URL: Issues, https://github.com/samhardyhey/clean-py/issues
Keywords: python,code-formatting,jupyter,notebook,black,isort,autoflake
Classifier: Development Status :: 4 - Beta
Classifier: Environment :: Console
Classifier: Intended Audience :: Developers
Classifier: License :: OSI Approved :: MIT License
Classifier: Programming Language :: Python :: 3
Classifier: Programming Language :: Python :: 3.6
Classifier: Programming Language :: Python :: 3.7
Classifier: Programming Language :: Python :: 3.8
Classifier: Programming Language :: Python :: 3.9
Classifier: Topic :: Software Development :: Libraries :: Python Modules
Classifier: Topic :: Software Development :: Quality Assurance
Requires-Python: >=3.6
License-File: LICENSE
Requires-Dist: black==25.1.0
Requires-Dist: isort==6.0.1
Requires-Dist: jupyter==1.1.1
Requires-Dist: autoflake==2.3.1
Requires-Dist: notebook<7.0.0
Requires-Dist: jupyter_contrib_nbextensions==0.7.0
Requires-Dist: nbconvert<7.0.0
Requires-Dist: pytest==8.3.5
Requires-Dist: pytest-cov==4.1.0
Requires-Dist: typer[all]==0.9.0
Provides-Extra: dev
Requires-Dist: build==1.2.2.post1; extra == "dev"
Requires-Dist: tox==4.24.2; extra == "dev"
Requires-Dist: twine==6.1.0; extra == "dev"
Requires-Dist: setuptools_scm==8.0.0; extra == "dev"
Requires-Dist: tox==4.24.2; extra == "dev"
Requires-Dist: pypi-cleanup==0.1.8; extra == "dev"
Dynamic: license-file
